ih_muse-0.0.25.dist-info/METADATA
ih_muse-0.0.25.dist-info/WHEEL
ih_muse/_utils/muse_version.py
ih_muse/muse/__init__.py
ih_muse/muse/muse.py
ih_muse/proto/__init__.py
ih_muse/proto/metric.py
ih_muse/proto/element_kind.py
ih_muse/config/config.py
ih_muse/config/__init__.py
ih_muse/ih_muse.pyi
ih_muse/exceptions.pyi
ih_muse/__init__.py
ih_muse/py.typed
ih_muse/exceptions.py
ih_muse/ih_muse.cpython-39-darwin.so
ih_muse-0.0.25.dist-info/RECORD
