Metadata-Version: 2.4
Name: ih-muse
Version: 0.0.25
Classifier: Intended Audience :: Developers
Classifier: Programming Language :: Python
Classifier: Programming Language :: Python :: 3
Classifier: Programming Language :: Python :: 3.9
Classifier: Programming Language :: Python :: 3.10
Classifier: Programming Language :: Python :: 3.11
Classifier: Programming Language :: Python :: 3.12
Classifier: Programming Language :: Python :: 3.13
Classifier: Topic :: Software Development :: Libraries :: Python Modules
Summary: Common muse library for python
Keywords: python
Author: Luis Diaz
Author-email: Luis Diaz <code.luis.diaz@proton.me
Requires-Python: >=3.9, <4.0
Project-URL: Homepage, https://infinitehaiku.github.io/ih-muse/
Project-URL: Repository, https://github.com/infinitehaiku/ih-muse
Project-URL: Documentation, https://infinitehaiku.github.io/ih-muse/
